sesamutils/__init__.py
sesamutils/dotdictify.py
sesamutils/flask.py
sesamutils/profiler.py
sesamutils/sesamlogger.py
sesamutils/variables.py
sesamutils/tests/__init__.py
sesamutils/tests/test_dotdictify.py
sesamutils/tests/test_sesamlogger.py
sesamutils/tests/test_variables.py
sesamutils-0.1.10.dist-info/LICENSE
sesamutils-0.1.10.dist-info/METADATA
sesamutils-0.1.10.dist-info/WHEEL
sesamutils-0.1.10.dist-info/top_level.txt
sesamutils-0.1.10.dist-info/RECORD
