Metadata-Version: 2.1
Name: sesamutils
Version: 0.1.10
Summary: Sesam microservice utils
Home-page: https://github.com/sesam-community/
Author: Anders Borud
License: UNKNOWN
Platform: UNKNOWN
Classifier: Programming Language :: Python
Classifier: Topic :: Internet :: WWW/HTTP
Requires-Dist: pytest
Requires-Dist: testfixtures
Requires-Dist: paste
Requires-Dist: CherryPy (==18.2.0)
